{
  "rodin/the-thinker": {
    "profile": "bronze-patina",
    "baseColor": "#6B4F31",
    "secondaryColor": "#31584E",
    "tintStrength": 0.72,
    "variation": 0.42,
    "metalness": 0.58,
    "roughness": 0.52,
    "textureDefault": 48,
    "exposure": 0.74,
    "envMapIntensity": 0.64,
    "emissiveIntensity": 0,
    "mapLift": 0.16,
    "mapFloor": 0.04,
    "backdropTop": "#15243A",
    "backdropBase": "#15243A",
    "backdropGlow": "#D7DEE8",
    "backdropGlowStrength": 0.07,
    "keyLightIntensity": 1.26,
    "fillLightIntensity": 0.9,
    "rimLightIntensity": 1.5,
    "hemiLightIntensity": 0.78
  },
  "americas/headdress-effigy-hareiga": {
    "profile": "wood",
    "baseColor": "#6A4A31",
    "secondaryColor": "#A07850",
    "tintStrength": 0.42,
    "variation": 0.32,
    "metalness": 0,
    "roughness": 0.66,
    "textureDefault": 42,
    "exposure": 0.72,
    "envMapIntensity": 0.35,
    "emissiveIntensity": 0,
    "mapLift": 0.34,
    "mapFloor": 0.12,
    "backdropTop": "#15243A",
    "backdropBase": "#15243A",
    "backdropGlow": "#D7DEE8",
    "backdropGlowStrength": 0.07,
    "keyLightIntensity": 1.18,
    "fillLightIntensity": 1,
    "rimLightIntensity": 1.38,
    "hemiLightIntensity": 0.9
  },
  "neoclassical/model-of-the-greek-slave-smithsonian": {
    "profile": "plaster",
    "baseColor": "#D0C6B8",
    "secondaryColor": "#C2B6A6",
    "tintStrength": 0.36,
    "variation": 0.08,
    "metalness": 0,
    "roughness": 0.82,
    "textureDefault": 26,
    "exposure": 0.72,
    "envMapIntensity": 0.2,
    "emissiveIntensity": 0,
    "mapLift": 0.66,
    "mapFloor": 0.22,
    "backdropTop": "#15243A",
    "backdropBase": "#15243A",
    "backdropGlow": "#D7DEE8",
    "backdropGlowStrength": 0.07,
    "keyLightIntensity": 1.22,
    "fillLightIntensity": 1.02,
    "rimLightIntensity": 1.24,
    "hemiLightIntensity": 0.98
  }
}
